setup.py
apt_yikes.egg-info/PKG-INFO
apt_yikes.egg-info/SOURCES.txt
apt_yikes.egg-info/dependency_links.txt
apt_yikes.egg-info/entry_points.txt
apt_yikes.egg-info/requires.txt
apt_yikes.egg-info/top_level.txt
script_gen/__init__.py
script_gen/__main__.py