Metadata-Version: 1.1
Name: apt-yikes
Version: 0.0.2
Summary: Makes a script to set up ubuntu boxes.
Home-page: https://github.com/yiwensong/ubuntu-setup
Author: yiwen song
Author-email: songzgy@gmail.com
License: MIT
Platform: UNKNOWN
Classifier: Natural Language :: English
Classifier: Programming Language :: Python :: 3.7
Classifier: License :: OSI Approved :: MIT License
